segmenthee/__init__.py
segmenthee/cart_api.py
segmenthee/config.py
segmenthee/parser_api.py
segmenthee/shop.py
segmentheepy_euro-1.0.2.dist-info/METADATA
segmentheepy_euro-1.0.2.dist-info/WHEEL
segmentheepy_euro-1.0.2.dist-info/top_level.txt
segmentheepy_euro-1.0.2.dist-info/RECORD
